CHANGELOG.rst
INTRO.rst
LICENSE
MANIFEST.in
PRODUCTS.rst
README.rst
setup.py
vmemclient/__init__.py
vmemclient/version.py
vmemclient.egg-info/PKG-INFO
vmemclient.egg-info/SOURCES.txt
vmemclient.egg-info/dependency_links.txt
vmemclient.egg-info/not-zip-safe
vmemclient.egg-info/top_level.txt
vmemclient/concerto/__init__.py
vmemclient/concerto/adapter.py
vmemclient/concerto/client.py
vmemclient/concerto/concerto.py
vmemclient/concerto/lun.py
vmemclient/concerto/pool.py
vmemclient/concerto/replication.py
vmemclient/concerto/snapshot.py
vmemclient/concerto/utility.py
vmemclient/core/__init__.py
vmemclient/core/error.py
vmemclient/core/node.py
vmemclient/core/request.py
vmemclient/core/response.py
vmemclient/core/restobject.py
vmemclient/core/session.py
vmemclient/data/version.dat
vmemclient/tests/__init__.py
vmemclient/tests/test_concerto01.py
vmemclient/tests/test_session.py
vmemclient/varray/__init__.py
vmemclient/varray/format.py
vmemclient/varray/varray.py
vmemclient/varray/vcm.py
vmemclient/vshare/__init__.py
vmemclient/vshare/igroup.py
vmemclient/vshare/iscsi.py
vmemclient/vshare/lun.py
vmemclient/vshare/snapshot.py
vmemclient/vshare/vshare.py