Metadata-Version: 1.1
Name: vmemclient
Version: 1.1.9
Summary: Violin Memory Client Interface Library
Home-page: http://www.vmem.com
Author: Violin Memory, Inc.
Author-email: opensource@vmem.com
License: Apache Version 2.0
Keywords: violin violinmemory vmem vmemclient rest
Platform: UNKNOWN
Classifier: Development Status :: 4 - Beta
Classifier: Intended Audience :: Developers
Classifier: Intended Audience :: System Administrators
Classifier: License :: OSI Approved :: Apache Software License
Classifier: Natural Language :: English
Classifier: Operating System :: OS Independent
Classifier: Programming Language :: Python :: 2
Classifier: Programming Language :: Python :: 2.6
Classifier: Programming Language :: Python :: 2.7
